Metadata-Version: 1.0
Name: calculate-distributions
Version: 1.0
Summary: Find Binomaial and Gaussian distributions
Home-page: UNKNOWN
Author: UNKNOWN
Author-email: UNKNOWN
License: UNKNOWN
Platform: UNKNOWN
